pysros/__init__.py
pysros/errors.py
pysros/exceptions.py
pysros/identifier.py
pysros/management.py
pysros/model.py
pysros/model_builder.py
pysros/model_defines.py
pysros/model_path.py
pysros/model_walker.py
pysros/path_utils.py
pysros/pprint.py
pysros/request_data.py
pysros/singleton.py
pysros/tokenizer.py
pysros/wrappers.py
pysros/yang_type.py
pysros-25.10.2.dist-info/licenses/LICENSE.md
pysros-25.10.2.dist-info/METADATA
pysros-25.10.2.dist-info/WHEEL
pysros-25.10.2.dist-info/top_level.txt
pysros-25.10.2.dist-info/RECORD
