Metadata-Version: 2.4
Name: pysros
Version: 25.10.2
Summary: Python for the Nokia Service Router Operating Systems (pySROS)
Home-page: https://www.nokia.com
Author: Nokia
Author-email: 
License: Copyright 2021-2025 Nokia.  License available in the LICENSE.md file.
Project-URL: Documentation, https://network.developer.nokia.com/static/sr/learn/pysros/latest/
Project-URL: Source, https://github.com/nokia/pysros
Classifier: License :: Other/Proprietary License
Classifier: Natural Language :: English
Classifier: Programming Language :: Python :: 3
Classifier: Topic :: Internet
Classifier: Development Status :: 5 - Production/Stable
Requires-Python: >=3.10
License-File: LICENSE.md
Requires-Dist: ncclient~=0.6.12
Requires-Dist: lxml~=5.3.0
Dynamic: author
Dynamic: classifier
Dynamic: description
Dynamic: description-content-type
Dynamic: home-page
Dynamic: license
Dynamic: license-file
Dynamic: project-url
Dynamic: requires-dist
Dynamic: requires-python
Dynamic: summary
